com/__init__.py
com/flourish/__init__.py
com/flourish/development/__init__.py
com/flourish/production/__init__.py
com/flourish/production/common/__init__.py
com/flourish/production/common/ingest/05_run_technical_dq_rules_on_table_before_source_aligning.py
com/flourish/production/common/ingest/06_source_align_raw_data_improved_mysql.py
com/flourish/production/common/ingest/06_source_align_raw_data_improved_redshift.py
com/flourish/production/common/ingest/06_source_align_raw_data_mysql.py
com/flourish/production/common/ingest/06_source_align_raw_data_redshift.py
com/flourish/production/common/ingest/06_source_align_raw_delta_data_mysql.py
com/flourish/production/common/ingest/06_source_align_raw_delta_data_redshift.py
com/flourish/production/common/ingest/06_source_align_raw_incremental_data_mysql.py
com/flourish/production/common/ingest/06_source_align_raw_incremental_data_redshift.py
com/flourish/production/common/ingest/07_run_technical_dq_rules_on_table.py
com/flourish/production/common/ingest/__init__.py
com/flourish/production/common/ingest/csv/00_create_raw_file_from_database_table.py
com/flourish/production/common/ingest/csv/01_move_raw_file_to_received_folder.py
com/flourish/production/common/ingest/csv/02_create_raw_table.py
com/flourish/production/common/ingest/csv/02_recreate_raw_table.py
com/flourish/production/common/ingest/csv/03_run_technical_dq_rules_on_file.py
com/flourish/production/common/ingest/csv/04_ingest_data_into_raw_table.py
com/flourish/production/common/ingest/csv/04_ingest_data_into_raw_table_improved.py
com/flourish/production/common/ingest/csv/04_ingest_data_into_raw_table_with_blank_columns_in_the_end.py
com/flourish/production/common/ingest/csv/04_ingest_data_into_raw_table_with_reporting_period.py
com/flourish/production/common/ingest/csv/__init__.py
com/flourish/production/common/ingest/excel/01_move_raw_file_to_received_folder.py
flourish_package-0.0.11.dist-info/LICENSE
flourish_package-0.0.11.dist-info/METADATA
flourish_package-0.0.11.dist-info/WHEEL
flourish_package-0.0.11.dist-info/top_level.txt
flourish_package-0.0.11.dist-info/RECORD
