Metadata-Version: 2.1
Name: flourish-package
Version: 0.0.11
Summary: This is a SaaS solution to create data pipelines and manage metadata for businesses (small and big).
Home-page: https://github.com/srinivaskrishnamurthy/flourish_package
Author: K S
Author-email: sk@stree.chat
License: : OSI Approved :: MIT License
Classifier: Programming Language :: Python :: 3
License-File: LICENSE
